hathitrustdownloader/__init__.py
hathitrustdownloader/cli.py
hathitrust_downloader-1.4.0.dist-info/LICENSE
hathitrust_downloader-1.4.0.dist-info/METADATA
hathitrust_downloader-1.4.0.dist-info/WHEEL
hathitrust_downloader-1.4.0.dist-info/entry_points.txt
hathitrust_downloader-1.4.0.dist-info/top_level.txt
hathitrust_downloader-1.4.0.dist-info/RECORD
