Metadata-Version: 2.1
Name: hathitrust-downloader
Version: 1.4.0
Summary: Downloads multiple pages from Hathitrust from the CLI.
Home-page: http://github.com/addono/hathitrust-downloader
Author: Adriaan Knapen
Author-email: hi@aknapen.nl
License: MIT
Keywords: hathitrust download downloader cli
Classifier: Development Status :: 6 - Mature
Classifier: Intended Audience :: Developers
Classifier: Operating System :: POSIX
Classifier: Operating System :: POSIX :: Linux
Classifier: License :: OSI Approved :: MIT License
Classifier: Programming Language :: Python :: 3
Classifier: Programming Language :: Python :: 3.9
Classifier: Programming Language :: Python :: 3.10
Classifier: Programming Language :: Python :: 3.11
Classifier: Programming Language :: Python :: 3.12
Classifier: Programming Language :: Python :: 3.13
License-File: LICENSE
Requires-Dist: requests==2.32.3
Requires-Dist: tqdm==4.66.5
